df_this/__init__.py
df_this/cli.py
df_this/main.py
df_this-0.1.2.dist-info/licenses/LICENSE
df_this-0.1.2.dist-info/METADATA
df_this-0.1.2.dist-info/WHEEL
df_this-0.1.2.dist-info/entry_points.txt
df_this-0.1.2.dist-info/top_level.txt
df_this-0.1.2.dist-info/RECORD
