Metadata-Version: 2.4
Name: df-this
Version: 0.1.2
Summary: A tool to inspect your incoming dataframes and excel files.
Author: nb0401
Project-URL: Homepage, https://github.com/nb0401/df-this
Project-URL: Source, https://github.com/nb0401/df-this
Project-URL: Issues, https://github.com/nb0401/df-this/issues
Requires-Python: >=3.8
License-File: LICENSE
Requires-Dist: pandas
Requires-Dist: openpyxl
Requires-Dist: tqdm
Dynamic: license-file
